{"expand":"operations,versionedRepresentations,editmeta,changelog,renderedFields","id":"11149","self":"http://localhost:8080/rest/api/2/issue/11149","key":"MYPROJECTID-412","fields":{"issuetype":{"self":"http://localhost:8080/rest/api/2/issuetype/4","id":"4","description":"samplevalueno4563","iconUrl":"http://localhost:8080/secure/viewavatar?size=xsmall&avatarId=12370&avatarType=issuetype","name":"Improvement","subtask":false,"avatarId":12370},"timespent":null,"project":{"self":"http://localhost:8080/rest/api/2/project/10060","id":"10060","key":"MYPROJECTID","name":"samplevalueno212","avatarUrls":{"48x48":"http://localhost:8080/secure/projectavatar?pid=10060&avatarId=10008","24x24":"http://localhost:8080/secure/projectavatar?size=small&pid=10060&avatarId=10008","16x16":"http://localhost:8080/secure/projectavatar?size=xsmall&pid=10060&avatarId=10008","32x32":"http://localhost:8080/secure/projectavatar?size=medium&pid=10060&avatarId=10008"},"projectCategory":{"self":"http://localhost:8080/rest/api/2/projectCategory/10020","id":"10020","description":"samplevalueno4472","name":"samplevalueno4456"}},"fixVersions":[],"aggregatetimespent":null,"resolution":{"self":"http://localhost:8080/rest/api/2/resolution/2","id":"2","description":"samplevalueno4535","name":"samplevalueno226"},"resolutiondate":"2014-12-02T15:50:16.000+0000","workratio":-1,"lastViewed":null,"watches":{"self":"http://localhost:8080/rest/api/2/issue/MYPROJECTID-412/watchers","watchCount":2,"isWatching":false},"created":"2011-12-06T23:58:04.000+0000","priority":{"self":"http://localhost:8080/rest/api/2/priority/4","iconUrl":"http://localhost:8080/images/icons/priorities/minor.svg","name":"samplevalueno18","id":"4"},"labels":[],"timeestimate":null,"aggregatetimeoriginalestimate":null,"issuelinks":[],"assignee":{"self":"http://localhost:8080/rest/api/2/user?username=chestergeoghegan","name":"chestergeoghegan","key":"chestergeoghegan","avatarUrls":{"48x48":"http://localhost:8080/secure/useravatar?avatarId=10082","24x24":"http://localhost:8080/secure/useravatar?size=small&avatarId=10082","16x16":"http://localhost:8080/secure/useravatar?size=xsmall&avatarId=10082","32x32":"http://localhost:8080/secure/useravatar?size=medium&avatarId=10082"},"displayName":"Chester Geoghegan","active":true,"timeZone":"America/Chicago"},"updated":"2014-12-02T15:50:16.000+0000","status":{"self":"http://localhost:8080/rest/api/2/status/6","description":"samplevalueno4474","iconUrl":"http://localhost:8080/images/icons/statuses/closed.png","name":"Closed","id":"6","statusCategory":{"self":"http://localhost:8080/rest/api/2/statusillalesseregory/3","id":3,"key":"done","colorName":"green","name":"samplevalueno4457"}},"components":[{"self":"http://localhost:8080/rest/api/2/component/10120","id":"10120","name":"component1","description":"samplevalueno4514"}],"timeoriginalestimate":null,"description":"samplevalueno910","aggregatetimeestimate":null,"summary":"samplevalueno909","creator":{"self":"http://localhost:8080/rest/api/2/user?username=filomenaphong","name":"filomenaphong","key":"filomenaphong","avatarUrls":{"48x48":"http://localhost:8080/secure/useravatar?ownerId=filomenaphong&avatarId=10960","24x24":"http://localhost:8080/secure/useravatar?size=small&ownerId=filomenaphong&avatarId=10960","16x16":"http://localhost:8080/secure/useravatar?size=xsmall&ownerId=filomenaphong&avatarId=10960","32x32":"http://localhost:8080/secure/useravatar?size=medium&ownerId=filomenaphong&avatarId=10960"},"displayName":"Filomena Phong","active":true,"timeZone":"America/Chicago"},"subtasks":[],"reporter":{"self":"http://localhost:8080/rest/api/2/user?username=filomenaphong","name":"filomenaphong","key":"filomenaphong","avatarUrls":{"48x48":"http://localhost:8080/secure/useravatar?ownerId=filomenaphong&avatarId=10960","24x24":"http://localhost:8080/secure/useravatar?size=small&ownerId=filomenaphong&avatarId=10960","16x16":"http://localhost:8080/secure/useravatar?size=xsmall&ownerId=filomenaphong&avatarId=10960","32x32":"http://localhost:8080/secure/useravatar?size=medium&ownerId=filomenaphong&avatarId=10960"},"displayName":"Filomena Phong","active":true,"timeZone":"America/Chicago"},"aggregateprogress":{"progress":0,"total":0},"duedate":null,"progress":{"progress":0,"total":0},"votes":{"self":"http://localhost:8080/rest/api/2/issue/MYPROJECTID-412/votes","votes":0,"hasVoted":false},"customfield_12345":5},"changelog":{"startAt":0,"maxResults":15,"total":15,"histories":[{"id":"12697","author":{"self":"http://localhost:8080/rest/api/2/user?username=ivonneomara","name":"ivonneomara","key":"ivonneomara","avatarUrls":{"48x48":"http://localhost:8080/secure/useravatar?avatarId=10082","24x24":"http://localhost:8080/secure/useravatar?size=small&avatarId=10082","16x16":"http://localhost:8080/secure/useravatar?size=xsmall&avatarId=10082","32x32":"http://localhost:8080/secure/useravatar?size=medium&avatarId=10082"},"displayName":"Ivonne Omara","active":true,"timeZone":"America/Chicago"},"created":"2011-12-14T00:16:38.000+0000","items":[{"field":"Component","fieldtype":"jira","from":null,"fromString":null,"to":"samplevalueno2266","toString":"component1"}]},{"id":"15597","author":{"self":"http://localhost:8080/rest/api/2/user?username=keiracoombe","name":"keiracoombe","key":"keiracoombe","avatarUrls":{"48x48":"http://localhost:8080/secure/useravatar?ownerId=keiracoombe&avatarId=10362","24x24":"http://localhost:8080/secure/useravatar?size=small&ownerId=keiracoombe&avatarId=10362","16x16":"http://localhost:8080/secure/useravatar?size=xsmall&ownerId=keiracoombe&avatarId=10362","32x32":"http://localhost:8080/secure/useravatar?size=medium&ownerId=keiracoombe&avatarId=10362"},"displayName":"Keira Coombe","active":false,"timeZone":"America/Chicago"},"created":"2012-09-05T18:48:12.000+0000","items":[{"field":"assignee","fieldtype":"jira","from":"keiracoombe","fromString":"Keira Coombe","to":null,"toString":null}]},{"id":"17746","author":{"self":"http://localhost:8080/rest/api/2/user?username=illalesser","name":"illalesser","key":"illalesser","avatarUrls":{"48x48":"http://localhost:8080/secure/useravatar?ownerId=illalesser&avatarId=12660","24x24":"http://localhost:8080/secure/useravatar?size=small&ownerId=illalesser&avatarId=12660","16x16":"http://localhost:8080/secure/useravatar?size=xsmall&ownerId=illalesser&avatarId=12660","32x32":"http://localhost:8080/secure/useravatar?size=medium&ownerId=illalesser&avatarId=12660"},"displayName":"Illa Lesser","active":true,"timeZone":"America/Chicago"},"created":"2013-01-17T14:35:01.000+0000","items":[{"field":"Workflow","fieldtype":"jira","from":"samplevalueno2289","fromString":"samplevalueno1","to":"samplevalueno2290","toString":"samplevalueno2"}]},{"id":"18659","author":{"self":"http://localhost:8080/rest/api/2/user?username=illalesser","name":"illalesser","key":"illalesser","avatarUrls":{"48x48":"http://localhost:8080/secure/useravatar?ownerId=illalesser&avatarId=12660","24x24":"http://localhost:8080/secure/useravatar?size=small&ownerId=illalesser&avatarId=12660","16x16":"http://localhost:8080/secure/useravatar?size=xsmall&ownerId=illalesser&avatarId=12660","32x32":"http://localhost:8080/secure/useravatar?size=medium&ownerId=illalesser&avatarId=12660"},"displayName":"Illa Lesser","active":true,"timeZone":"America/Chicago"},"created":"2013-01-17T15:18:16.000+0000","items":[{"field":"Workflow","fieldtype":"jira","from":"samplevalueno2290","fromString":"samplevalueno2","to":"samplevalueno3848","toString":"samplevalueno545"}]},{"id":"23968","author":{"self":"http://localhost:8080/rest/api/2/user?username=illalesser","name":"illalesser","key":"illalesser","avatarUrls":{"48x48":"http://localhost:8080/secure/useravatar?ownerId=illalesser&avatarId=12660","24x24":"http://localhost:8080/secure/useravatar?size=small&ownerId=illalesser&avatarId=12660","16x16":"http://localhost:8080/secure/useravatar?size=xsmall&ownerId=illalesser&avatarId=12660","32x32":"http://localhost:8080/secure/useravatar?size=medium&ownerId=illalesser&avatarId=12660"},"displayName":"Illa Lesser","active":true,"timeZone":"America/Chicago"},"created":"2013-08-15T16:45:55.000+0000","items":[{"field":"priority","fieldtype":"jira","from":"samplevalueno1330","fromString":"samplevalueno4","to":"samplevalueno1339","toString":"samplevalueno18"}]},{"id":"23969","author":{"self":"http://localhost:8080/rest/api/2/user?username=illalesser","name":"illalesser","key":"illalesser","avatarUrls":{"48x48":"http://localhost:8080/secure/useravatar?ownerId=illalesser&avatarId=12660","24x24":"http://localhost:8080/secure/useravatar?size=small&ownerId=illalesser&avatarId=12660","16x16":"http://localhost:8080/secure/useravatar?size=xsmall&ownerId=illalesser&avatarId=12660","32x32":"http://localhost:8080/secure/useravatar?size=medium&ownerId=illalesser&avatarId=12660"},"displayName":"Illa Lesser","active":true,"timeZone":"America/Chicago"},"created":"2013-08-15T16:46:11.000+0000","items":[{"field":"assignee","fieldtype":"jira","from":null,"fromString":null,"to":"chestergeoghegan","toString":"Chester Geoghegan"}]},{"id":"24005","author":{"self":"http://localhost:8080/rest/api/2/user?username=chestergeoghegan","name":"chestergeoghegan","key":"chestergeoghegan","avatarUrls":{"48x48":"http://localhost:8080/secure/useravatar?avatarId=10082","24x24":"http://localhost:8080/secure/useravatar?size=small&avatarId=10082","16x16":"http://localhost:8080/secure/useravatar?size=xsmall&avatarId=10082","32x32":"http://localhost:8080/secure/useravatar?size=medium&avatarId=10082"},"displayName":"Chester Geoghegan","active":true,"timeZone":"America/Chicago"},"created":"2013-08-15T20:34:02.000+0000","items":[{"field":"description","fieldtype":"jira","from":null,"fromString":"samplevalueno250","to":null,"toString":"samplevalueno251"}]},{"id":"24006","author":{"self":"http://localhost:8080/rest/api/2/user?username=chestergeoghegan","name":"chestergeoghegan","key":"chestergeoghegan","avatarUrls":{"48x48":"http://localhost:8080/secure/useravatar?avatarId=10082","24x24":"http://localhost:8080/secure/useravatar?size=small&avatarId=10082","16x16":"http://localhost:8080/secure/useravatar?size=xsmall&avatarId=10082","32x32":"http://localhost:8080/secure/useravatar?size=medium&avatarId=10082"},"displayName":"Chester Geoghegan","active":true,"timeZone":"America/Chicago"},"created":"2013-08-15T20:43:33.000+0000","items":[{"field":"description","fieldtype":"jira","from":null,"fromString":"samplevalueno251","to":null,"toString":"samplevalueno252"}]},{"id":"24007","author":{"self":"http://localhost:8080/rest/api/2/user?username=chestergeoghegan","name":"chestergeoghegan","key":"chestergeoghegan","avatarUrls":{"48x48":"http://localhost:8080/secure/useravatar?avatarId=10082","24x24":"http://localhost:8080/secure/useravatar?size=small&avatarId=10082","16x16":"http://localhost:8080/secure/useravatar?size=xsmall&avatarId=10082","32x32":"http://localhost:8080/secure/useravatar?size=medium&avatarId=10082"},"displayName":"Chester Geoghegan","active":true,"timeZone":"America/Chicago"},"created":"2013-08-15T20:43:58.000+0000","items":[{"field":"description","fieldtype":"jira","from":null,"fromString":"samplevalueno252","to":null,"toString":"samplevalueno253"}]},{"id":"24008","author":{"self":"http://localhost:8080/rest/api/2/user?username=chestergeoghegan","name":"chestergeoghegan","key":"chestergeoghegan","avatarUrls":{"48x48":"http://localhost:8080/secure/useravatar?avatarId=10082","24x24":"http://localhost:8080/secure/useravatar?size=small&avatarId=10082","16x16":"http://localhost:8080/secure/useravatar?size=xsmall&avatarId=10082","32x32":"http://localhost:8080/secure/useravatar?size=medium&avatarId=10082"},"displayName":"Chester Geoghegan","active":true,"timeZone":"America/Chicago"},"created":"2013-08-15T20:45:32.000+0000","items":[{"field":"description","fieldtype":"jira","from":null,"fromString":"samplevalueno253","to":null,"toString":"samplevalueno254"}]},{"id":"24009","author":{"self":"http://localhost:8080/rest/api/2/user?username=chestergeoghegan","name":"chestergeoghegan","key":"chestergeoghegan","avatarUrls":{"48x48":"http://localhost:8080/secure/useravatar?avatarId=10082","24x24":"http://localhost:8080/secure/useravatar?size=small&avatarId=10082","16x16":"http://localhost:8080/secure/useravatar?size=xsmall&avatarId=10082","32x32":"http://localhost:8080/secure/useravatar?size=medium&avatarId=10082"},"displayName":"Chester Geoghegan","active":true,"timeZone":"America/Chicago"},"created":"2013-08-15T20:57:41.000+0000","items":[{"field":"description","fieldtype":"jira","from":null,"fromString":"samplevalueno254","to":null,"toString":"samplevalueno256"}]},{"id":"24010","author":{"self":"http://localhost:8080/rest/api/2/user?username=chestergeoghegan","name":"chestergeoghegan","key":"chestergeoghegan","avatarUrls":{"48x48":"http://localhost:8080/secure/useravatar?avatarId=10082","24x24":"http://localhost:8080/secure/useravatar?size=small&avatarId=10082","16x16":"http://localhost:8080/secure/useravatar?size=xsmall&avatarId=10082","32x32":"http://localhost:8080/secure/useravatar?size=medium&avatarId=10082"},"displayName":"Chester Geoghegan","active":true,"timeZone":"America/Chicago"},"created":"2013-08-15T21:00:13.000+0000","items":[{"field":"summary","fieldtype":"jira","from":null,"fromString":"samplevalueno255","to":null,"toString":"samplevalueno909"}]},{"id":"24012","author":{"self":"http://localhost:8080/rest/api/2/user?username=illalesser","name":"illalesser","key":"illalesser","avatarUrls":{"48x48":"http://localhost:8080/secure/useravatar?ownerId=illalesser&avatarId=12660","24x24":"http://localhost:8080/secure/useravatar?size=small&ownerId=illalesser&avatarId=12660","16x16":"http://localhost:8080/secure/useravatar?size=xsmall&ownerId=illalesser&avatarId=12660","32x32":"http://localhost:8080/secure/useravatar?size=medium&ownerId=illalesser&avatarId=12660"},"displayName":"Illa Lesser","active":true,"timeZone":"America/Chicago"},"created":"2013-08-16T13:58:35.000+0000","items":[{"field":"description","fieldtype":"jira","from":null,"fromString":"samplevalueno256","to":null,"toString":"samplevalueno257"}]},{"id":"24013","author":{"self":"http://localhost:8080/rest/api/2/user?username=illalesser","name":"illalesser","key":"illalesser","avatarUrls":{"48x48":"http://localhost:8080/secure/useravatar?ownerId=illalesser&avatarId=12660","24x24":"http://localhost:8080/secure/useravatar?size=small&ownerId=illalesser&avatarId=12660","16x16":"http://localhost:8080/secure/useravatar?size=xsmall&ownerId=illalesser&avatarId=12660","32x32":"http://localhost:8080/secure/useravatar?size=medium&ownerId=illalesser&avatarId=12660"},"displayName":"Illa Lesser","active":true,"timeZone":"America/Chicago"},"created":"2013-08-16T13:59:49.000+0000","items":[{"field":"description","fieldtype":"jira","from":null,"fromString":"samplevalueno257","to":null,"toString":"samplevalueno910"}]}]}}