{"expand":"operations,versionedRepresentations,editmeta,changelog,renderedFields","id":"12785","self":"http://localhost:8080/rest/api/2/issue/12785","key":"MYPROJECTID-807","fields":{"issuetype":{"self":"http://localhost:8080/rest/api/2/issuetype/1","id":"1","description":"samplevalueno4494","iconUrl":"http://localhost:8080/secure/viewavatar?size=xsmall&avatarId=12363&avatarType=issuetype","name":"Bug","subtask":false,"avatarId":12363},"timespent":null,"project":{"self":"http://localhost:8080/rest/api/2/project/10060","id":"10060","key":"MYPROJECTID","name":"samplevalueno212","avatarUrls":{"48x48":"http://localhost:8080/secure/projectavatar?pid=10060&avatarId=10008","24x24":"http://localhost:8080/secure/projectavatar?size=small&pid=10060&avatarId=10008","16x16":"http://localhost:8080/secure/projectavatar?size=xsmall&pid=10060&avatarId=10008","32x32":"http://localhost:8080/secure/projectavatar?size=medium&pid=10060&avatarId=10008"},"projectCategory":{"self":"http://localhost:8080/rest/api/2/projectCategory/10020","id":"10020","description":"samplevalueno4472","name":"samplevalueno4456"}},"fixVersions":[],"aggregatetimespent":null,"resolution":{"self":"http://localhost:8080/rest/api/2/resolution/1","id":"1","description":"samplevalueno4473","name":"samplevalueno3"},"resolutiondate":"2012-10-29T19:45:15.000+0000","workratio":-1,"lastViewed":null,"watches":{"self":"http://localhost:8080/rest/api/2/issue/MYPROJECTID-807/watchers","watchCount":2,"isWatching":false},"created":"2012-10-09T17:07:37.000+0000","priority":{"self":"http://localhost:8080/rest/api/2/priority/4","iconUrl":"http://localhost:8080/images/icons/priorities/minor.svg","name":"samplevalueno18","id":"4"},"labels":[],"timeestimate":null,"aggregatetimeoriginalestimate":null,"issuelinks":[],"assignee":{"self":"http://localhost:8080/rest/api/2/user?username=myrnastabile","name":"myrnastabile","key":"myrnastabile","avatarUrls":{"48x48":"http://localhost:8080/secure/useravatar?ownerId=myrnastabile&avatarId=12060","24x24":"http://localhost:8080/secure/useravatar?size=small&ownerId=myrnastabile&avatarId=12060","16x16":"http://localhost:8080/secure/useravatar?size=xsmall&ownerId=myrnastabile&avatarId=12060","32x32":"http://localhost:8080/secure/useravatar?size=medium&ownerId=myrnastabile&avatarId=12060"},"displayName":"Myrna Stabile","active":true,"timeZone":"America/Chicago"},"updated":"2012-11-06T20:38:37.000+0000","status":{"self":"http://localhost:8080/rest/api/2/status/6","description":"samplevalueno4474","iconUrl":"http://localhost:8080/images/icons/statuses/closed.png","name":"Closed","id":"6","statusCategory":{"self":"http://localhost:8080/rest/api/2/statusillalesseregory/3","id":3,"key":"done","colorName":"green","name":"samplevalueno4457"}},"components":[{"self":"http://localhost:8080/rest/api/2/component/10122","id":"10122","name":"component18","description":"samplevalueno4506"}],"timeoriginalestimate":null,"description":"samplevalueno4881","aggregatetimeestimate":null,"summary":"samplevalueno6234","creator":{"self":"http://localhost:8080/rest/api/2/user?username=myrnastabile","name":"myrnastabile","key":"myrnastabile","avatarUrls":{"48x48":"http://localhost:8080/secure/useravatar?ownerId=myrnastabile&avatarId=12060","24x24":"http://localhost:8080/secure/useravatar?size=small&ownerId=myrnastabile&avatarId=12060","16x16":"http://localhost:8080/secure/useravatar?size=xsmall&ownerId=myrnastabile&avatarId=12060","32x32":"http://localhost:8080/secure/useravatar?size=medium&ownerId=myrnastabile&avatarId=12060"},"displayName":"Myrna Stabile","active":true,"timeZone":"America/Chicago"},"subtasks":[],"reporter":{"self":"http://localhost:8080/rest/api/2/user?username=myrnastabile","name":"myrnastabile","key":"myrnastabile","avatarUrls":{"48x48":"http://localhost:8080/secure/useravatar?ownerId=myrnastabile&avatarId=12060","24x24":"http://localhost:8080/secure/useravatar?size=small&ownerId=myrnastabile&avatarId=12060","16x16":"http://localhost:8080/secure/useravatar?size=xsmall&ownerId=myrnastabile&avatarId=12060","32x32":"http://localhost:8080/secure/useravatar?size=medium&ownerId=myrnastabile&avatarId=12060"},"displayName":"Myrna Stabile","active":true,"timeZone":"America/Chicago"},"aggregateprogress":{"progress":0,"total":0},"duedate":null,"progress":{"progress":0,"total":0},"votes":{"self":"http://localhost:8080/rest/api/2/issue/MYPROJECTID-807/votes","votes":0,"hasVoted":false},"customfield_12345":6},"changelog":{"startAt":0,"maxResults":5,"total":5,"histories":[{"id":"16112","author":{"self":"http://localhost:8080/rest/api/2/user?username=myrnastabile","name":"myrnastabile","key":"myrnastabile","avatarUrls":{"48x48":"http://localhost:8080/secure/useravatar?ownerId=myrnastabile&avatarId=12060","24x24":"http://localhost:8080/secure/useravatar?size=small&ownerId=myrnastabile&avatarId=12060","16x16":"http://localhost:8080/secure/useravatar?size=xsmall&ownerId=myrnastabile&avatarId=12060","32x32":"http://localhost:8080/secure/useravatar?size=medium&ownerId=myrnastabile&avatarId=12060"},"displayName":"Myrna Stabile","active":true,"timeZone":"America/Chicago"},"created":"2012-10-09T20:34:21.000+0000","items":[{"field":"status","fieldtype":"jira","from":"samplevalueno1308","fromString":"Open","to":"samplevalueno1330","toString":"In Progress"}]},{"id":"16290","author":{"self":"http://localhost:8080/rest/api/2/user?username=myrnastabile","name":"myrnastabile","key":"myrnastabile","avatarUrls":{"48x48":"http://localhost:8080/secure/useravatar?ownerId=myrnastabile&avatarId=12060","24x24":"http://localhost:8080/secure/useravatar?size=small&ownerId=myrnastabile&avatarId=12060","16x16":"http://localhost:8080/secure/useravatar?size=xsmall&ownerId=myrnastabile&avatarId=12060","32x32":"http://localhost:8080/secure/useravatar?size=medium&ownerId=myrnastabile&avatarId=12060"},"displayName":"Myrna Stabile","active":true,"timeZone":"America/Chicago"},"created":"2012-10-29T19:45:15.000+0000","items":[{"field":"status","fieldtype":"jira","from":"samplevalueno1330","fromString":"In Progress","to":"samplevalueno1309","toString":"Resolved"},{"field":"resolution","fieldtype":"jira","from":null,"fromString":null,"to":"samplevalueno1308","toString":"samplevalueno3"}]},{"id":"16420","author":{"self":"http://localhost:8080/rest/api/2/user?username=myrnastabile","name":"myrnastabile","key":"myrnastabile","avatarUrls":{"48x48":"http://localhost:8080/secure/useravatar?ownerId=myrnastabile&avatarId=12060","24x24":"http://localhost:8080/secure/useravatar?size=small&ownerId=myrnastabile&avatarId=12060","16x16":"http://localhost:8080/secure/useravatar?size=xsmall&ownerId=myrnastabile&avatarId=12060","32x32":"http://localhost:8080/secure/useravatar?size=medium&ownerId=myrnastabile&avatarId=12060"},"displayName":"Myrna Stabile","active":true,"timeZone":"America/Chicago"},"created":"2012-11-06T20:38:37.000+0000","items":[{"field":"status","fieldtype":"jira","from":"samplevalueno1309","fromString":"Resolved","to":"samplevalueno1381","toString":"Closed"}]},{"id":"18611","author":{"self":"http://localhost:8080/rest/api/2/user?username=illalesser","name":"illalesser","key":"illalesser","avatarUrls":{"48x48":"http://localhost:8080/secure/useravatar?ownerId=illalesser&avatarId=12660","24x24":"http://localhost:8080/secure/useravatar?size=small&ownerId=illalesser&avatarId=12660","16x16":"http://localhost:8080/secure/useravatar?size=xsmall&ownerId=illalesser&avatarId=12660","32x32":"http://localhost:8080/secure/useravatar?size=medium&ownerId=illalesser&avatarId=12660"},"displayName":"Illa Lesser","active":true,"timeZone":"America/Chicago"},"created":"2013-01-17T14:35:09.000+0000","items":[{"field":"Workflow","fieldtype":"jira","from":"samplevalueno1841","fromString":"samplevalueno1","to":"samplevalueno1842","toString":"samplevalueno2"}]},{"id":"19524","author":{"self":"http://localhost:8080/rest/api/2/user?username=illalesser","name":"illalesser","key":"illalesser","avatarUrls":{"48x48":"http://localhost:8080/secure/useravatar?ownerId=illalesser&avatarId=12660","24x24":"http://localhost:8080/secure/useravatar?size=small&ownerId=illalesser&avatarId=12660","16x16":"http://localhost:8080/secure/useravatar?size=xsmall&ownerId=illalesser&avatarId=12660","32x32":"http://localhost:8080/secure/useravatar?size=medium&ownerId=illalesser&avatarId=12660"},"displayName":"Illa Lesser","active":true,"timeZone":"America/Chicago"},"created":"2013-01-17T15:18:39.000+0000","items":[{"field":"Workflow","fieldtype":"jira","from":"samplevalueno1842","fromString":"samplevalueno2","to":"samplevalueno3562","toString":"samplevalueno545"}]}]}}