{"expand":"operations,versionedRepresentations,editmeta,changelog,renderedFields","id":"15359","self":"http://localhost:8080/rest/api/2/issue/15359","key":"MYPROJECTID-1336","fields":{"issuetype":{"self":"http://localhost:8080/rest/api/2/issuetype/3","id":"3","description":"samplevalueno4477","iconUrl":"http://localhost:8080/secure/viewavatar?size=xsmall&avatarId=12378&avatarType=issuetype","name":"Task","subtask":false,"avatarId":12378},"timespent":null,"project":{"self":"http://localhost:8080/rest/api/2/project/10060","id":"10060","key":"MYPROJECTID","name":"samplevalueno212","avatarUrls":{"48x48":"http://localhost:8080/secure/projectavatar?pid=10060&avatarId=10008","24x24":"http://localhost:8080/secure/projectavatar?size=small&pid=10060&avatarId=10008","16x16":"http://localhost:8080/secure/projectavatar?size=xsmall&pid=10060&avatarId=10008","32x32":"http://localhost:8080/secure/projectavatar?size=medium&pid=10060&avatarId=10008"},"projectCategory":{"self":"http://localhost:8080/rest/api/2/projectCategory/10020","id":"10020","description":"samplevalueno4472","name":"samplevalueno4456"}},"fixVersions":[{"self":"http://localhost:8080/rest/api/2/version/11610","id":"11610","description":"samplevalueno5619","name":"label17","archived":false,"released":true,"releaseDate":"2014-03-11"},{"self":"http://localhost:8080/rest/api/2/version/11612","id":"11612","description":"samplevalueno5621","name":"label41","archived":false,"released":true,"releaseDate":"2014-03-11"}],"aggregatetimespent":null,"resolution":{"self":"http://localhost:8080/rest/api/2/resolution/1","id":"1","description":"samplevalueno4473","name":"samplevalueno3"},"resolutiondate":"2014-03-11T16:26:42.000+0000","workratio":-1,"lastViewed":null,"watches":{"self":"http://localhost:8080/rest/api/2/issue/MYPROJECTID-1336/watchers","watchCount":8,"isWatching":false},"created":"2013-12-18T15:03:29.000+0000","priority":{"self":"http://localhost:8080/rest/api/2/priority/3","iconUrl":"http://localhost:8080/images/icons/priorities/major.svg","name":"samplevalueno4","id":"3"},"labels":["label17","label41"],"timeestimate":null,"aggregatetimeoriginalestimate":null,"issuelinks":[{"id":"13814","self":"http://localhost:8080/rest/api/2/issueLink/13814","type":{"id":"10010","name":"samplevalueno4460","inward":"has to be done after","outward":"has to be done before","self":"http://localhost:8080/rest/api/2/issueLinkType/10010"},"outwardIssue":{"id":"15406","key":null,"self":"http://localhost:8080/rest/api/2/issue/15406","fields":{"summary":"samplevalueno7002","status":{"self":"http://localhost:8080/rest/api/2/status/6","description":"samplevalueno4474","iconUrl":"http://localhost:8080/images/icons/statuses/closed.png","name":"Closed","id":"6","statusCategory":{"self":"http://localhost:8080/rest/api/2/statusillalesseregory/3","id":3,"key":"done","colorName":"green","name":"samplevalueno4457"}},"priority":{"self":"http://localhost:8080/rest/api/2/priority/3","iconUrl":"http://localhost:8080/images/icons/priorities/major.svg","name":"samplevalueno4","id":"3"},"issuetype":{"self":"http://localhost:8080/rest/api/2/issuetype/3","id":"3","description":"samplevalueno4477","iconUrl":"http://localhost:8080/secure/viewavatar?size=xsmall&avatarId=12378&avatarType=issuetype","name":"Task","subtask":false,"avatarId":12378}}}}],"assignee":{"self":"http://localhost:8080/rest/api/2/user?username=samuelshain","name":"samuelshain","key":"samuelshain","avatarUrls":{"48x48":"http://localhost:8080/secure/useravatar?avatarId=10082","24x24":"http://localhost:8080/secure/useravatar?size=small&avatarId=10082","16x16":"http://localhost:8080/secure/useravatar?size=xsmall&avatarId=10082","32x32":"http://localhost:8080/secure/useravatar?size=medium&avatarId=10082"},"displayName":"Samuel Shain","active":true,"timeZone":"America/Havana"},"updated":"2014-03-11T16:26:42.000+0000","status":{"self":"http://localhost:8080/rest/api/2/status/6","description":"samplevalueno4474","iconUrl":"http://localhost:8080/images/icons/statuses/closed.png","name":"Closed","id":"6","statusCategory":{"self":"http://localhost:8080/rest/api/2/statusillalesseregory/3","id":3,"key":"done","colorName":"green","name":"samplevalueno4457"}},"components":[{"self":"http://localhost:8080/rest/api/2/component/10024","id":"10024","name":"label29","description":"samplevalueno4724"},{"self":"http://localhost:8080/rest/api/2/component/10122","id":"10122","name":"component18","description":"samplevalueno4506"}],"timeoriginalestimate":null,"description":"samplevalueno5620","aggregatetimeestimate":null,"summary":"samplevalueno7001","creator":{"self":"http://localhost:8080/rest/api/2/user?username=jacqulinegutshall","name":"jacqulinegutshall","key":"jacqulinegutshall","avatarUrls":{"48x48":"http://localhost:8080/secure/useravatar?avatarId=10082","24x24":"http://localhost:8080/secure/useravatar?size=small&avatarId=10082","16x16":"http://localhost:8080/secure/useravatar?size=xsmall&avatarId=10082","32x32":"http://localhost:8080/secure/useravatar?size=medium&avatarId=10082"},"displayName":"Jacquline Gutshall","active":true,"timeZone":"Etc/UTC"},"subtasks":[],"reporter":{"self":"http://localhost:8080/rest/api/2/user?username=jacqulinegutshall","name":"jacqulinegutshall","key":"jacqulinegutshall","avatarUrls":{"48x48":"http://localhost:8080/secure/useravatar?avatarId=10082","24x24":"http://localhost:8080/secure/useravatar?size=small&avatarId=10082","16x16":"http://localhost:8080/secure/useravatar?size=xsmall&avatarId=10082","32x32":"http://localhost:8080/secure/useravatar?size=medium&avatarId=10082"},"displayName":"Jacquline Gutshall","active":true,"timeZone":"Etc/UTC"},"aggregateprogress":{"progress":0,"total":0},"duedate":null,"progress":{"progress":0,"total":0},"votes":{"self":"http://localhost:8080/rest/api/2/issue/MYPROJECTID-1336/votes","votes":0,"hasVoted":false},"customfield_12345":3},"changelog":{"startAt":0,"maxResults":19,"total":19,"histories":[{"id":"26067","author":{"self":"http://localhost:8080/rest/api/2/user?username=illalesser","name":"illalesser","key":"illalesser","avatarUrls":{"48x48":"http://localhost:8080/secure/useravatar?ownerId=illalesser&avatarId=12660","24x24":"http://localhost:8080/secure/useravatar?size=small&ownerId=illalesser&avatarId=12660","16x16":"http://localhost:8080/secure/useravatar?size=xsmall&ownerId=illalesser&avatarId=12660","32x32":"http://localhost:8080/secure/useravatar?size=medium&ownerId=illalesser&avatarId=12660"},"displayName":"Illa Lesser","active":true,"timeZone":"America/Chicago"},"created":"2013-12-18T17:28:50.000+0000","items":[{"field":"assignee","fieldtype":"jira","from":null,"fromString":null,"to":"samplevalueno1423","toString":"Catarina Stuckey"}]},{"id":"26068","author":{"self":"http://localhost:8080/rest/api/2/user?username=illalesser","name":"illalesser","key":"illalesser","avatarUrls":{"48x48":"http://localhost:8080/secure/useravatar?ownerId=illalesser&avatarId=12660","24x24":"http://localhost:8080/secure/useravatar?size=small&ownerId=illalesser&avatarId=12660","16x16":"http://localhost:8080/secure/useravatar?size=xsmall&ownerId=illalesser&avatarId=12660","32x32":"http://localhost:8080/secure/useravatar?size=medium&ownerId=illalesser&avatarId=12660"},"displayName":"Illa Lesser","active":true,"timeZone":"America/Chicago"},"created":"2013-12-18T17:29:38.000+0000","items":[{"field":"assignee","fieldtype":"jira","from":"samplevalueno1423","fromString":"Catarina Stuckey","to":null,"toString":null}]},{"id":"26073","author":{"self":"http://localhost:8080/rest/api/2/user?username=illalesser","name":"illalesser","key":"illalesser","avatarUrls":{"48x48":"http://localhost:8080/secure/useravatar?ownerId=illalesser&avatarId=12660","24x24":"http://localhost:8080/secure/useravatar?size=small&ownerId=illalesser&avatarId=12660","16x16":"http://localhost:8080/secure/useravatar?size=xsmall&ownerId=illalesser&avatarId=12660","32x32":"http://localhost:8080/secure/useravatar?size=medium&ownerId=illalesser&avatarId=12660"},"displayName":"Illa Lesser","active":true,"timeZone":"America/Chicago"},"created":"2013-12-18T19:28:19.000+0000","items":[{"field":"assignee","fieldtype":"jira","from":null,"fromString":null,"to":"samplevalueno1423","toString":"Catarina Stuckey"}]}]}}