{"expand":"operations,versionedRepresentations,editmeta,changelog,renderedFields","id":"11285","self":"http://localhost:8080/rest/api/2/issue/11285","key":"MYPROJECTID-467","fields":{"issuetype":{"self":"http://localhost:8080/rest/api/2/issuetype/9","id":"9","description":"samplevalueno4471","iconUrl":"http://localhost:8080/secure/viewavatar?size=xsmall&avatarId=12366&avatarType=issuetype","name":"Documentation","subtask":false,"avatarId":12366},"timespent":null,"project":{"self":"http://localhost:8080/rest/api/2/project/10060","id":"10060","key":"MYPROJECTID","name":"samplevalueno212","avatarUrls":{"48x48":"http://localhost:8080/secure/projectavatar?pid=10060&avatarId=10008","24x24":"http://localhost:8080/secure/projectavatar?size=small&pid=10060&avatarId=10008","16x16":"http://localhost:8080/secure/projectavatar?size=xsmall&pid=10060&avatarId=10008","32x32":"http://localhost:8080/secure/projectavatar?size=medium&pid=10060&avatarId=10008"},"projectCategory":{"self":"http://localhost:8080/rest/api/2/projectCategory/10020","id":"10020","description":"samplevalueno4472","name":"samplevalueno4456"}},"fixVersions":[],"aggregatetimespent":null,"resolution":{"self":"http://localhost:8080/rest/api/2/resolution/1","id":"1","description":"samplevalueno4473","name":"samplevalueno3"},"resolutiondate":"2012-01-24T22:31:39.000+0000","workratio":-1,"lastViewed":null,"watches":{"self":"http://localhost:8080/rest/api/2/issue/MYPROJECTID-467/watchers","watchCount":0,"isWatching":false},"created":"2012-01-09T21:16:12.000+0000","priority":{"self":"http://localhost:8080/rest/api/2/priority/4","iconUrl":"http://localhost:8080/images/icons/priorities/minor.svg","name":"samplevalueno18","id":"4"},"labels":[],"timeestimate":null,"aggregatetimeoriginalestimate":null,"issuelinks":[],"assignee":{"self":"http://localhost:8080/rest/api/2/user?username=lutherlamoreaux","name":"lutherlamoreaux","key":"lutherlamoreaux","avatarUrls":{"48x48":"http://localhost:8080/secure/useravatar?avatarId=10082","24x24":"http://localhost:8080/secure/useravatar?size=small&avatarId=10082","16x16":"http://localhost:8080/secure/useravatar?size=xsmall&avatarId=10082","32x32":"http://localhost:8080/secure/useravatar?size=medium&avatarId=10082"},"displayName":"Luther Lamoreaux","active":false,"timeZone":"Etc/UTC"},"updated":"2013-05-10T15:51:27.000+0000","status":{"self":"http://localhost:8080/rest/api/2/status/6","description":"samplevalueno4474","iconUrl":"http://localhost:8080/images/icons/statuses/closed.png","name":"Closed","id":"6","statusCategory":{"self":"http://localhost:8080/rest/api/2/statusillalesseregory/3","id":3,"key":"done","colorName":"green","name":"samplevalueno4457"}},"components":[{"self":"http://localhost:8080/rest/api/2/component/10220","id":"10220","name":"label16","description":"Documentation"}],"timeoriginalestimate":null,"description":"samplevalueno965","aggregatetimeestimate":null,"summary":"samplevalueno964","creator":{"self":"http://localhost:8080/rest/api/2/user?username=lutherlamoreaux","name":"lutherlamoreaux","key":"lutherlamoreaux","avatarUrls":{"48x48":"http://localhost:8080/secure/useravatar?avatarId=10082","24x24":"http://localhost:8080/secure/useravatar?size=small&avatarId=10082","16x16":"http://localhost:8080/secure/useravatar?size=xsmall&avatarId=10082","32x32":"http://localhost:8080/secure/useravatar?size=medium&avatarId=10082"},"displayName":"Luther Lamoreaux","active":false,"timeZone":"Etc/UTC"},"subtasks":[],"reporter":{"self":"http://localhost:8080/rest/api/2/user?username=lutherlamoreaux","name":"lutherlamoreaux","key":"lutherlamoreaux","avatarUrls":{"48x48":"http://localhost:8080/secure/useravatar?avatarId=10082","24x24":"http://localhost:8080/secure/useravatar?size=small&avatarId=10082","16x16":"http://localhost:8080/secure/useravatar?size=xsmall&avatarId=10082","32x32":"http://localhost:8080/secure/useravatar?size=medium&avatarId=10082"},"displayName":"Luther Lamoreaux","active":false,"timeZone":"Etc/UTC"},"aggregateprogress":{"progress":0,"total":0},"duedate":null,"progress":{"progress":0,"total":0},"votes":{"self":"http://localhost:8080/rest/api/2/issue/MYPROJECTID-467/votes","votes":0,"hasVoted":false},"customfield_12345":2},"changelog":{"startAt":0,"maxResults":7,"total":7,"histories":[{"id":"12868","author":{"self":"http://localhost:8080/rest/api/2/user?username=keiracoombe","name":"keiracoombe","key":"keiracoombe","avatarUrls":{"48x48":"http://localhost:8080/secure/useravatar?ownerId=keiracoombe&avatarId=10362","24x24":"http://localhost:8080/secure/useravatar?size=small&ownerId=keiracoombe&avatarId=10362","16x16":"http://localhost:8080/secure/useravatar?size=xsmall&ownerId=keiracoombe&avatarId=10362","32x32":"http://localhost:8080/secure/useravatar?size=medium&ownerId=keiracoombe&avatarId=10362"},"displayName":"Keira Coombe","active":false,"timeZone":"America/Chicago"},"created":"2012-01-09T21:38:56.000+0000","items":[{"field":"Component","fieldtype":"jira","from":null,"fromString":null,"to":"samplevalueno3210","toString":"label16"}]},{"id":"12871","author":{"self":"http://localhost:8080/rest/api/2/user?username=keiracoombe","name":"keiracoombe","key":"keiracoombe","avatarUrls":{"48x48":"http://localhost:8080/secure/useravatar?ownerId=keiracoombe&avatarId=10362","24x24":"http://localhost:8080/secure/useravatar?size=small&ownerId=keiracoombe&avatarId=10362","16x16":"http://localhost:8080/secure/useravatar?size=xsmall&ownerId=keiracoombe&avatarId=10362","32x32":"http://localhost:8080/secure/useravatar?size=medium&ownerId=keiracoombe&avatarId=10362"},"displayName":"Keira Coombe","active":false,"timeZone":"America/Chicago"},"created":"2012-01-09T22:53:27.000+0000","items":[{"field":"summary","fieldtype":"jira","from":null,"fromString":"samplevalueno306","to":null,"toString":"samplevalueno964"},{"field":"assignee","fieldtype":"jira","from":"keiracoombe","fromString":"Keira Coombe","to":"lutherlamoreaux","toString":"Luther Lamoreaux"},{"field":"description","fieldtype":"jira","from":null,"fromString":"samplevalueno307","to":null,"toString":"samplevalueno965"}]},{"id":"12974","author":{"self":"http://localhost:8080/rest/api/2/user?username=lutherlamoreaux","name":"lutherlamoreaux","key":"lutherlamoreaux","avatarUrls":{"48x48":"http://localhost:8080/secure/useravatar?avatarId=10082","24x24":"http://localhost:8080/secure/useravatar?size=small&avatarId=10082","16x16":"http://localhost:8080/secure/useravatar?size=xsmall&avatarId=10082","32x32":"http://localhost:8080/secure/useravatar?size=medium&avatarId=10082"},"displayName":"Luther Lamoreaux","active":false,"timeZone":"Etc/UTC"},"created":"2012-01-24T22:31:39.000+0000","items":[{"field":"status","fieldtype":"jira","from":"samplevalueno1308","fromString":"Open","to":"samplevalueno1309","toString":"Resolved"},{"field":"resolution","fieldtype":"jira","from":null,"fromString":null,"to":"samplevalueno1308","toString":"samplevalueno3"}]},{"id":"17937","author":{"self":"http://localhost:8080/rest/api/2/user?username=illalesser","name":"illalesser","key":"illalesser","avatarUrls":{"48x48":"http://localhost:8080/secure/useravatar?ownerId=illalesser&avatarId=12660","24x24":"http://localhost:8080/secure/useravatar?size=small&ownerId=illalesser&avatarId=12660","16x16":"http://localhost:8080/secure/useravatar?size=xsmall&ownerId=illalesser&avatarId=12660","32x32":"http://localhost:8080/secure/useravatar?size=medium&ownerId=illalesser&avatarId=12660"},"displayName":"Illa Lesser","active":true,"timeZone":"America/Chicago"},"created":"2013-01-17T14:35:02.000+0000","items":[{"field":"Workflow","fieldtype":"jira","from":"samplevalueno2460","fromString":"samplevalueno1","to":"samplevalueno2461","toString":"samplevalueno2"}]},{"id":"18850","author":{"self":"http://localhost:8080/rest/api/2/user?username=illalesser","name":"illalesser","key":"illalesser","avatarUrls":{"48x48":"http://localhost:8080/secure/useravatar?ownerId=illalesser&avatarId=12660","24x24":"http://localhost:8080/secure/useravatar?size=small&ownerId=illalesser&avatarId=12660","16x16":"http://localhost:8080/secure/useravatar?size=xsmall&ownerId=illalesser&avatarId=12660","32x32":"http://localhost:8080/secure/useravatar?size=medium&ownerId=illalesser&avatarId=12660"},"displayName":"Illa Lesser","active":true,"timeZone":"America/Chicago"},"created":"2013-01-17T15:18:24.000+0000","items":[{"field":"Workflow","fieldtype":"jira","from":"samplevalueno2461","fromString":"samplevalueno2","to":"samplevalueno3946","toString":"samplevalueno545"},{"field":"status","fieldtype":"jira","from":"samplevalueno1309","fromString":"Resolved","to":"samplevalueno1420","toString":"Ready for Testing"}]},{"id":"22125","author":{"self":"http://localhost:8080/rest/api/2/user?username=illalesser","name":"illalesser","key":"illalesser","avatarUrls":{"48x48":"http://localhost:8080/secure/useravatar?ownerId=illalesser&avatarId=12660","24x24":"http://localhost:8080/secure/useravatar?size=small&ownerId=illalesser&avatarId=12660","16x16":"http://localhost:8080/secure/useravatar?size=xsmall&ownerId=illalesser&avatarId=12660","32x32":"http://localhost:8080/secure/useravatar?size=medium&ownerId=illalesser&avatarId=12660"},"displayName":"Illa Lesser","active":true,"timeZone":"America/Chicago"},"created":"2013-05-10T15:51:23.000+0000","items":[{"field":"status","fieldtype":"jira","from":"samplevalueno1420","fromString":"Ready for Testing","to":"samplevalueno1421","toString":"Ready for Release"}]},{"id":"22126","author":{"self":"http://localhost:8080/rest/api/2/user?username=illalesser","name":"illalesser","key":"illalesser","avatarUrls":{"48x48":"http://localhost:8080/secure/useravatar?ownerId=illalesser&avatarId=12660","24x24":"http://localhost:8080/secure/useravatar?size=small&ownerId=illalesser&avatarId=12660","16x16":"http://localhost:8080/secure/useravatar?size=xsmall&ownerId=illalesser&avatarId=12660","32x32":"http://localhost:8080/secure/useravatar?size=medium&ownerId=illalesser&avatarId=12660"},"displayName":"Illa Lesser","active":true,"timeZone":"America/Chicago"},"created":"2013-05-10T15:51:27.000+0000","items":[{"field":"status","fieldtype":"jira","from":"samplevalueno1421","fromString":"Ready for Release","to":"samplevalueno1381","toString":"Closed"}]}]}}